{
 "grama": {
  "arquivo": "proc/grama.png",
  "tipo": "tile",
  "tema": "floresta",
  "origem": "IA",
  "bytes": 139987
 },
 "caminho": {
  "arquivo": "proc/caminho.png",
  "tipo": "tile",
  "tema": "floresta",
  "origem": "IA",
  "bytes": 261154
 },
 "arvore": {
  "arquivo": "proc/arvore.png",
  "tipo": "objeto",
  "tema": "floresta",
  "origem": "IA",
  "bytes": 45075
 },
 "flores": {
  "arquivo": "proc/flores.png",
  "tipo": "objeto",
  "tema": "floresta",
  "origem": "IA",
  "bytes": 54449
 },
 "muro": {
  "arquivo": "proc/muro.png",
  "tipo": "tile",
  "tema": "floresta",
  "origem": "IA",
  "bytes": 128738
 },
 "byte": {
  "arquivo": "proc/byte.png",
  "tipo": "personagem",
  "tema": "base",
  "origem": "IA",
  "bytes": 38330
 },
 "chave": {
  "arquivo": "proc/chave.png",
  "tipo": "objeto",
  "tema": "base",
  "origem": "IA",
  "bytes": 2595
 },
 "passarinho": {
  "arquivo": "proc/passarinho.png",
  "tipo": "bicho",
  "tema": "floresta",
  "origem": "IA",
  "bytes": 5186
 },
 "borboleta": {
  "arquivo": "proc/borboleta.png",
  "tipo": "bicho",
  "tema": "floresta",
  "origem": "IA",
  "bytes": 58994
 },
 "gato": {
  "arquivo": "proc/gato.png",
  "tipo": "personagem",
  "tema": "floresta",
  "origem": "IA",
  "bytes": 14979
 },
 "coelho": {
  "arquivo": "proc/coelho.png",
  "tipo": "personagem",
  "tema": "floresta",
  "origem": "IA",
  "bytes": 4787
 },
 "nimbo": {
  "arquivo": "proc/nimbo.png",
  "tipo": "personagem",
  "tema": "floresta",
  "origem": "IA",
  "bytes": 6829
 },
 "jaula": {
  "arquivo": "proc/jaula.png",
  "tipo": "objeto",
  "tema": "floresta",
  "origem": "IA",
  "bytes": 17939
 },
 "seta": {
  "arquivo": "proc/seta.png",
  "tipo": "objeto",
  "tema": "floresta",
  "origem": "IA",
  "bytes": 11237
 },
 "cabana": {
  "arquivo": "proc/cabana.png",
  "tipo": "objeto",
  "tema": "floresta",
  "origem": "IA",
  "bytes": 34062
 },
 "conves": {
  "arquivo": "proc/conves.png",
  "tipo": "tile",
  "tema": "navio",
  "origem": "IA",
  "bytes": 64294
 },
 "mar": {
  "arquivo": "proc/mar.png",
  "tipo": "tile",
  "tema": "navio",
  "origem": "IA",
  "bytes": 72593
 },
 "barril": {
  "arquivo": "proc/barril.png",
  "tipo": "objeto",
  "tema": "navio",
  "origem": "IA",
  "bytes": 67366
 },
 "bau": {
  "arquivo": "proc/bau.png",
  "tipo": "objeto",
  "tema": "navio",
  "origem": "IA",
  "bytes": 57485
 }
}